cpe_engine/__init__.py
cpe_engine/catalogs/__init__.py
cpe_engine/catalogs/official_catalogs.py
cpe_engine/catalogs/sunat_official/catalogo_01.json
cpe_engine/catalogs/sunat_official/catalogo_02.json
cpe_engine/catalogs/sunat_official/catalogo_03.json
cpe_engine/catalogs/sunat_official/catalogo_04.json
cpe_engine/catalogs/sunat_official/catalogo_05.json
cpe_engine/catalogs/sunat_official/catalogo_06.json
cpe_engine/catalogs/sunat_official/catalogo_07.json
cpe_engine/catalogs/sunat_official/catalogo_08.json
cpe_engine/catalogs/sunat_official/catalogo_09.json
cpe_engine/catalogs/sunat_official/catalogo_10.json
cpe_engine/catalogs/sunat_official/catalogo_11.json
cpe_engine/catalogs/sunat_official/catalogo_12.json
cpe_engine/catalogs/sunat_official/catalogo_14.json
cpe_engine/catalogs/sunat_official/catalogo_15.json
cpe_engine/catalogs/sunat_official/catalogo_16.json
cpe_engine/catalogs/sunat_official/catalogo_17.json
cpe_engine/catalogs/sunat_official/catalogo_18.json
cpe_engine/catalogs/sunat_official/catalogo_19.json
cpe_engine/catalogs/sunat_official/catalogo_20.json
cpe_engine/catalogs/sunat_official/catalogo_21.json
cpe_engine/catalogs/sunat_official/catalogo_22.json
cpe_engine/catalogs/sunat_official/catalogo_23.json
cpe_engine/catalogs/sunat_official/catalogo_24.json
cpe_engine/catalogs/sunat_official/catalogo_26.json
cpe_engine/catalogs/sunat_official/catalogo_27.json
cpe_engine/catalogs/sunat_official/catalogo_51.json
cpe_engine/catalogs/sunat_official/catalogo_52.json
cpe_engine/catalogs/sunat_official/catalogo_53.json
cpe_engine/catalogs/sunat_official/catalogo_54.json
cpe_engine/catalogs/sunat_official/catalogo_55.json
cpe_engine/catalogs/sunat_official/catalogo_56.json
cpe_engine/catalogs/sunat_official/catalogo_57.json
cpe_engine/catalogs/sunat_official/catalogo_58.json
cpe_engine/catalogs/sunat_official/catalogo_59.json
cpe_engine/catalogs/sunat_official/catalogo_60.json
cpe_engine/core/__init__.py
cpe_engine/core/builders/__init__.py
cpe_engine-0.2.6.dist-info/licenses/LICENSE
cpe_engine-0.2.6.dist-info/METADATA
cpe_engine-0.2.6.dist-info/WHEEL
cpe_engine-0.2.6.dist-info/top_level.txt
cpe_engine-0.2.6.dist-info/RECORD
