Metadata-Version: 2.4
Name: cpe-engine
Version: 0.2.6
Summary: Sistema de Emisión del Contribuyente - Facturación Electrónica Peruana
Author-email: Quanta Solutions <suma@bequanta.com>
License: MIT
Keywords: peru,sunat,facturacion,electronica,ubl,invoice,xml
Classifier: Development Status :: 4 - Beta
Classifier: Intended Audience :: Developers
Classifier: License :: OSI Approved :: MIT License
Classifier: Programming Language :: Python :: 3
Classifier: Programming Language :: Python :: 3.11
Classifier: Topic :: Office/Business :: Financial
Classifier: Topic :: Software Development :: Libraries :: Python Modules
Classifier: Operating System :: OS Independent
Requires-Python: >=3.11.6
License-File: LICENSE
Requires-Dist: jinja2>=3.1.0
Requires-Dist: lxml>=4.9.0
Requires-Dist: requests>=2.28.0
Requires-Dist: signxml>=3.2.0
Requires-Dist: pytz>=2023.3
Requires-Dist: pydantic>=2.0.0
Provides-Extra: dev
Requires-Dist: pytest>=7.0.0; extra == "dev"
Requires-Dist: pytest-cov>=4.0.0; extra == "dev"
Requires-Dist: black>=23.0.0; extra == "dev"
Requires-Dist: isort>=5.12.0; extra == "dev"
Requires-Dist: mypy>=1.5.0; extra == "dev"
Dynamic: license-file
